snowflake/__init__.py
snowflake/snowflake.py
snowflake_id-1.0.1.dist-info/METADATA
snowflake_id-1.0.1.dist-info/WHEEL
snowflake_id-1.0.1.dist-info/licenses/LICENSE
snowflake_id-1.0.1.dist-info/RECORD
