Metadata-Version: 2.1
Name: snowflake-id
Version: 1.0.1
Summary: The Snowflake generator done right
Keywords: snowflake snowflake-id id ids generator
Home-page: https://github.com/vd2org/snowflake
Author-Email: vd <snowflake@vd2.org>
License: MIT License
Classifier: Development Status :: 5 - Production/Stable
Classifier: Intended Audience :: Developers
Classifier: Intended Audience :: Information Technology
Classifier: Intended Audience :: System Administrators
Classifier: Topic :: Software Development
Classifier: Topic :: Software Development :: Libraries
Classifier: Topic :: Software Development :: Libraries :: Python Modules
Classifier: Topic :: Software Development :: User Interfaces
Classifier: License :: OSI Approved :: MIT License
Classifier: Programming Language :: Python :: 3
Classifier: Programming Language :: Python :: 3.8
Classifier: Programming Language :: Python :: 3.9
Classifier: Programming Language :: Python :: 3.10
Classifier: Programming Language :: Python :: 3.11
Classifier: Programming Language :: Python :: 3.12
Project-URL: Homepage, https://github.com/vd2org/snowflake
Project-URL: Repository, https://github.com/vd2org/snowflake.git
Project-URL: Issues, https://github.com/vd2org/snowflake/issues
Requires-Python: <3.13,>=3.8
